venta_protocol_v3_device/__init__.py
venta_protocol_v3_device-0.1.5.dist-info/METADATA
venta_protocol_v3_device-0.1.5.dist-info/WHEEL
venta_protocol_v3_device-0.1.5.dist-info/top_level.txt
venta_protocol_v3_device-0.1.5.dist-info/RECORD
